{
  "$schema": "https://ramams06.github.io/btech-registry/schema/registry-item.json",
  "name": "data-table",
  "type": "registry:ui",
  "title": "BTDataTable",
  "description": "Full-featured data table — sticky/fixed columns, checkbox selection, expandable rows, an optional toolbar (search + filters + actions) and built-in pagination.",
  "framework": "flutter",
  "category": "organisms",
  "figmaUrl": "https://www.figma.com/design/WANr9drWYNYbMPuT2sMeHi/Btech---Design-System?node-id=2373-11585",
  "figmaNodeId": "2373-11585",
  "dependencies": [
    "btech_tokens",
    "flutter_svg:^2.0.10+1"
  ],
  "devDependencies": [],
  "registryDependencies": [
    "badge",
    "button",
    "button-link",
    "checkbox",
    "dropdown",
    "dropdown-list",
    "hint",
    "input",
    "input-search",
    "pagination",
    "radio-button",
    "switch-field",
    "tag"
  ],
  "files": [
    {
      "path": "bt_data_table.dart",
      "target": "@flutterBase/data-table/bt_data_table.dart",
      "type": "registry:ui",
      "content": "// BTDataTable barrel — organisms/data_table\nexport 'bt_data_table.types.dart';\nexport 'bt_data_table.widget.dart';\n"
    },
    {
      "path": "bt_data_table.types.dart",
      "target": "@flutterBase/data-table/bt_data_table.types.dart",
      "type": "registry:ui",
      "content": "// BTDataTable types — organisms/data_table\n\n/// Cell content type within a data table.\nenum BTTableCellType {\n  text,\n  button,\n  doubleButton,\n  checkbox,\n  radio,\n  option,\n  field,\n  dropdown,\n  multipleSelection,\n  badge,\n  toggle,\n  number,\n}\n\n/// Visual variant of the data table.\nenum BTDataTableVariant {\n  /// Default — white row background, white header background.\n  defaultVariant,\n\n  /// Secondary — header uses brand.primarySubtle.\n  secondary,\n\n  /// No fill — transparent background.\n  noFill,\n}\n\n/// Sort direction for a sortable column.\nenum BTDataTableSortDirection { asc, desc, none }\n\n/// A selectable option inside a cell (dropdown / option cells).\nclass BTDataTableOption {\n  const BTDataTableOption({required this.label, required this.value});\n\n  final String label;\n  final String value;\n}\n\n/// A tag rendered inside a multiple-selection table cell.\nclass BTDataTableTag {\n  const BTDataTableTag({required this.label, this.id});\n\n  final String label;\n  final String? id;\n}\n\n/// The content model for a single table cell.\n///\n/// [type] controls how the cell is rendered.\n/// Not all fields apply to every type — unused fields are silently ignored.\nclass BTDataTableCell {\n  const BTDataTableCell({\n    this.type = BTTableCellType.text,\n    this.value,\n    this.label,\n    this.badgeLabel,\n    this.options = const [],\n    this.tags = const [],\n    this.checked = false,\n    this.selected = false,\n    this.disabled = false,\n  });\n\n  final BTTableCellType type;\n\n  /// Primary value — used by text, number, field, dropdown (selected key).\n  final dynamic value;\n\n  /// Display label — used by button, badge.\n  final String? label;\n\n  /// Badge label text (overrides [label] for badge cells).\n  final String? badgeLabel;\n\n  /// Options list for option / dropdown cells.\n  final List<BTDataTableOption> options;\n\n  /// Tags list for multiple-selection cells.\n  final List<BTDataTableTag> tags;\n\n  /// Checked state for checkbox / toggle cells.\n  final bool checked;\n\n  /// Selected state for radio cells.\n  final bool selected;\n\n  /// Disabled state — suppresses interaction.\n  final bool disabled;\n}\n\n/// Column definition for the data table.\nclass BTDataTableColumn {\n  const BTDataTableColumn({\n    required this.key,\n    required this.label,\n    this.width,\n    this.fill = false,\n    this.sortable = true,\n    this.sortDirection = BTDataTableSortDirection.none,\n    this.headerType = 'title',\n    this.expander = false,\n    this.align = BTDataTableColumnAlign.start,\n  });\n\n  /// Unique key matching [BTDataTableRow.cells] map keys.\n  final String key;\n\n  /// Header label text (displayed uppercase).\n  final String label;\n\n  /// Fixed column width in logical pixels. Ignored when [fill] is true.\n  final double? width;\n\n  /// When true, column expands to fill remaining space.\n  final bool fill;\n\n  /// Shows a sort indicator in the header.\n  final bool sortable;\n\n  /// Current sort direction. [BTDataTableSortDirection.none] shows no arrow.\n  final BTDataTableSortDirection sortDirection;\n\n  /// Header cell type: 'title' | 'checkbox-title' | 'title-dropdown'.\n  final String headerType;\n\n  /// Renders the tree expand/collapse arrow in this column.\n  final bool expander;\n\n  /// Cell content alignment.\n  final BTDataTableColumnAlign align;\n}\n\n/// Cell content alignment.\nenum BTDataTableColumnAlign { start, center, end }\n\n/// A single data row in the table.\nclass BTDataTableRow {\n  const BTDataTableRow({\n    required this.id,\n    required this.cells,\n    this.children,\n  });\n\n  /// Unique row identifier.\n  final String id;\n\n  /// Cell content keyed by [BTDataTableColumn.key].\n  /// Values may be [BTDataTableCell] or plain [String]/[num]/[bool].\n  final Map<String, dynamic> cells;\n\n  /// Nested child rows for tree display.\n  final List<BTDataTableRow>? children;\n}\n\n// ── Payload types ─────────────────────────────────────────────────────────────\n\n/// Payload emitted by [BTDataTable.onAction].\nclass BTTableActionPayload {\n  const BTTableActionPayload({\n    required this.action,\n    this.rowId,\n    this.columnKey,\n  });\n\n  /// Action identifier: 'filter' | 'download' | 'upload' | 'create' |\n  /// 'check-all' | 'check-row' | 'sort'.\n  final String action;\n\n  final String? rowId;\n  final String? columnKey;\n}\n\n/// Payload emitted by [BTDataTable.onCellChange].\nclass BTDataTableCellChangePayload {\n  const BTDataTableCellChangePayload({\n    required this.rowId,\n    required this.columnKey,\n    required this.cell,\n  });\n\n  final String rowId;\n  final String columnKey;\n  final BTDataTableCell cell;\n}\n\n/// Payload emitted by [BTDataTable.onSortChanged].\nclass BTSortPayload {\n  const BTSortPayload({\n    required this.columnKey,\n    required this.direction,\n  });\n\n  final String columnKey;\n  final BTDataTableSortDirection direction;\n}\n"
    },
    {
      "path": "bt_data_table.widget.dart",
      "target": "@flutterBase/data-table/bt_data_table.widget.dart",
      "type": "registry:ui",
      "content": "/// BTDataTable — compact data table organism.\n///\n/// Supports flat and tree-structured rows, multi-column sorting, row selection\n/// with tri-state header checkbox, filter tags, search, and pagination.\n///\n/// All colors use `context.btColor.*` — reactive to light/dark theme.\n///\n/// ## Usage — flat table:\n/// ```dart\n/// BTDataTable(\n///   title: 'Users',\n///   columns: const [\n///     BTDataTableColumn(key: 'name', label: 'Name', fill: true),\n///     BTDataTableColumn(key: 'status', label: 'Status', width: 120),\n///   ],\n///   rows: _rows,\n///   hasCheckbox: true,\n///   selectedRows: _selected,\n///   onSelectedRowsChanged: (ids) => setState(() => _selected = ids),\n///   onCellChange: (p) => print('${p.rowId} / ${p.columnKey}'),\n/// )\n/// ```\n///\n/// ## Usage — tree table:\n/// ```dart\n/// BTDataTable(\n///   columns: treeColumns,\n///   rows: treeRows,\n///   expandedKeys: _expandedKeys,\n///   onExpandedKeysChanged: (keys) => setState(() => _expandedKeys = keys),\n///   showPagination: false,\n/// )\n/// ```\nlibrary;\n\nimport 'dart:math' show max, min;\n\nimport 'package:btech_tokens/btech_tokens.dart';\nimport '../button/button.types.dart';\nimport '../button/button.widget.dart';\nimport '../button-link/button_link.widget.dart';\nimport '../dropdown-list/dropdown_list.types.dart';\nimport '../hint/hint.dart';\nimport '../tag/tag.widget.dart';\nimport '../dropdown/dropdown.widget.dart';\nimport '../input-search/input_search.widget.dart';\nimport '../pagination/pagination.widget.dart';\nimport 'package:btech_ui/src/components/organisms/data_table/bt_data_table.types.dart';\nimport 'package:btech_ui/src/components/organisms/data_table/internal/bt_table_row.dart';\nimport 'package:btech_ui/src/components/organisms/data_table/internal/bt_table_title.dart';\nimport 'package:flutter/material.dart';\n\n/// Compact data table organism. See file header for usage examples.\nclass BTDataTable extends StatefulWidget {\n  const BTDataTable({\n    this.title = 'Table Title',\n    this.columns = const [],\n    this.rows = const [],\n    this.variant = BTDataTableVariant.defaultVariant,\n    this.showToolbar = true,\n    this.showSearch = true,\n    this.showFilter = true,\n    this.showPagination = true,\n    this.searchValue = '',\n    this.rowsPerPage = 10,\n    this.rowsPerPageOptions = const [10, 20, 50],\n    this.currentPage = 1,\n    this.totalPages = 5,\n    this.filters = const [],\n    this.maxVisibleFilters = 4,\n    this.expandedKeys = const {},\n    this.maxHeight,\n    this.fixedHeader = false,\n    this.hasCheckbox = false,\n    this.fixedLeft = 0,\n    this.fixedRight = 0,\n    this.headerMinHeight = 32,\n    this.rowMinHeight = 68,\n    this.selectedRows = const [],\n    this.toolbarActions,\n    this.onSearchValueChanged,\n    this.onSearchSubmit,\n    this.onPageChange,\n    this.onRowsChange,\n    this.onAction,\n    this.onCellChange,\n    this.onRemoveFilter,\n    this.onRemoveAllFilters,\n    this.onExpandedKeysChanged,\n    this.onSortChanged,\n    this.onSelectedRowsChanged,\n    super.key,\n  });\n\n  final String title;\n  final List<BTDataTableColumn> columns;\n  final List<BTDataTableRow> rows;\n  final BTDataTableVariant variant;\n\n  final bool showToolbar;\n  final bool showSearch;\n  final bool showFilter;\n  final bool showPagination;\n\n  final String searchValue;\n  final int rowsPerPage;\n  final List<int> rowsPerPageOptions;\n  final int currentPage;\n  final int totalPages;\n\n  /// Filter tag labels shown below the toolbar.\n  final List<String> filters;\n\n  /// Maximum filter tags to show before \"+ N more\".\n  final int maxVisibleFilters;\n\n  /// Map of row id → expanded state for tree rows.\n  final Map<String, bool> expandedKeys;\n\n  /// When set, the body area is capped at this height with internal scrolling.\n  /// `null` = auto height.\n  final double? maxHeight;\n\n  /// Keeps the header visible while the body scrolls vertically when\n  /// [maxHeight] is set.\n  final bool fixedHeader;\n\n  final bool hasCheckbox;\n\n  /// Number of columns to pin from the left. Checkbox counts as one column\n  /// when [hasCheckbox] is true, matching the web DataTable API.\n  final int fixedLeft;\n\n  /// Number of data columns to pin from the right, matching the web API.\n  final int fixedRight;\n\n  /// Minimum header height. Use a compact value (e.g. 32) for text-only tables.\n  final double headerMinHeight;\n\n  /// Minimum body row height. Use a compact value (e.g. 32) for text-only tables.\n  final double rowMinHeight;\n\n  final List<String> selectedRows;\n\n  /// Optional widget slot rendered in the toolbar actions area.\n  /// When provided, replaces the default Download/Upload/Create buttons.\n  final Widget? toolbarActions;\n\n  // Callbacks\n  final ValueChanged<String>? onSearchValueChanged;\n  final ValueChanged<String>? onSearchSubmit;\n  final ValueChanged<int>? onPageChange;\n  final ValueChanged<int>? onRowsChange;\n  final ValueChanged<BTTableActionPayload>? onAction;\n  final ValueChanged<BTDataTableCellChangePayload>? onCellChange;\n  final ValueChanged<String>? onRemoveFilter;\n  final VoidCallback? onRemoveAllFilters;\n  final ValueChanged<Map<String, bool>>? onExpandedKeysChanged;\n  final ValueChanged<BTSortPayload>? onSortChanged;\n  final ValueChanged<List<String>>? onSelectedRowsChanged;\n\n  @override\n  State<BTDataTable> createState() => _BTDataTableState();\n}\n\nclass _BTDataTableState extends State<BTDataTable> {\n  // ── Scroll controllers ─────────────────────────────────────────────────────\n\n  late final ValueNotifier<double> _hScrollOffset;\n\n  /// Drives vertical scroll when [maxHeight] is set.\n  late final ScrollController _vScrollCtrl;\n\n  @override\n  void initState() {\n    super.initState();\n    _hScrollOffset = ValueNotifier<double>(0);\n    _vScrollCtrl = ScrollController();\n  }\n\n  @override\n  void dispose() {\n    _hScrollOffset.dispose();\n    _vScrollCtrl.dispose();\n    super.dispose();\n  }\n\n  // ── Column widths ──────────────────────────────────────────────────────────\n\n  /// Per-column auto-fit width cache — measured from header label + all cell\n  /// content. Recomputed when rows/columns change.\n  Map<String, double>? _autoWidthCache;\n  int _autoWidthCacheKey = -1;\n\n  /// Hash that invalidates the auto-width cache. Includes `expandedKeys` so\n  /// expander columns recompute when tree rows expand/collapse — the visible\n  /// depth changes, so the column needs to grow or shrink accordingly.\n  int get _columnCacheKey => Object.hash(\n        widget.columns.length,\n        widget.rows.length,\n        widget.hasCheckbox,\n        // Use ONLY the truthy keys count + their joined hash so equal expansion\n        // states map to equal keys regardless of map iteration order.\n        Object.hashAll(\n          widget.expandedKeys.entries\n              .where((e) => e.value)\n              .map((e) => e.key)\n              .toList()\n            ..sort(),\n        ),\n      );\n\n  /// Computes pixel widths for each column given a container width.\n  ///\n  /// Resolution priority per column:\n  /// 1. `col.fill == true` → splits remaining space equally\n  /// 2. `col.width != null` → fixed\n  /// 3. Otherwise → auto-fit to content (header + all cells, 8px padding)\n  List<double> _computeColumnWidths(double containerWidth) {\n    final checkboxW = widget.hasCheckbox ? kCheckboxWidth : 0.0;\n    final available = containerWidth - checkboxW;\n\n    // Invalidate auto-width cache when rows/columns change\n    if (_autoWidthCache == null || _autoWidthCacheKey != _columnCacheKey) {\n      _autoWidthCache = {\n        for (final col in widget.columns)\n          if (col.width == null && !col.fill) col.key: _measureColumnWidth(col),\n      };\n      _autoWidthCacheKey = _columnCacheKey;\n    }\n\n    double fixed = 0;\n    int fillCount = 0;\n    for (final col in widget.columns) {\n      if (col.fill) {\n        fillCount++;\n      } else if (col.width != null) {\n        fixed += col.width!;\n      } else {\n        fixed += _autoWidthCache![col.key] ?? 120.0;\n      }\n    }\n\n    final fillWidth = fillCount > 0\n        ? ((available - fixed) / fillCount).clamp(80.0, 400.0)\n        : 0.0;\n\n    return widget.columns.map((col) {\n      if (col.fill) return fillWidth;\n      if (col.width != null) return col.width!;\n      return _autoWidthCache![col.key] ?? 120.0;\n    }).toList();\n  }\n\n  /// Measures the natural width a column needs to fit its header + all cells.\n  /// Returns measured width clamped to [kColumnMinWidth..kColumnMaxWidth] with\n  /// 16px (8px×2) horizontal padding.\n  ///\n  /// Min-width 135px matches Figma D-DataTable spec (node 2373-11580).\n  double _measureColumnWidth(BTDataTableColumn col) {\n    const padding = 16.0; // 8px left + 8px right\n    const minWidth = 135.0; // Figma spec — default column min-width\n    // Expander columns can need much more width due to depth-based indent;\n    // give them headroom up to ~640px, others stay capped at 400.\n    final maxWidth = col.expander ? 640.0 : 400.0;\n\n    double measureText(String text, double size, FontWeight weight) {\n      if (text.isEmpty) return 0;\n      final painter = TextPainter(\n        text: TextSpan(\n          text: text,\n          style: TextStyle(fontSize: size, fontWeight: weight, height: 1.4),\n        ),\n        textDirection: TextDirection.ltr,\n        maxLines: 1,\n      )..layout();\n      return painter.width;\n    }\n\n    // Header label (uppercase, 11/600)\n    double maxContentW = measureText(\n      col.label.toUpperCase(),\n      11,\n      FontWeight.w600,\n    );\n    if (col.sortable) maxContentW += 20; // sort icon + gap\n\n    // Measure VISIBLE rows only — depth tracked so expander column accounts\n    // for tree indent (matches `_buildDataCell` in bt_table_row.dart):\n    //   _expanderIndent = 4 + (depth-1) * 24   for depth >= 1\n    //   + 16 (chevron / leaf placeholder)\n    //   + 4 (gap before content)\n    //\n    // Children are only traversed when their parent is expanded — collapsed\n    // subtrees don't contribute to the column width. This means the column\n    // dynamically grows/shrinks as the user expands/collapses rows.\n    void traverse(List<BTDataTableRow> rows, int depth) {\n      for (final row in rows) {\n        final raw = row.cells[col.key];\n        final BTDataTableCell? cell = raw is BTDataTableCell ? raw : null;\n        double w = 0;\n\n        if (cell != null) {\n          switch (cell.type) {\n            case BTTableCellType.text:\n            case BTTableCellType.number:\n              w = measureText(\n                cell.value?.toString() ?? '',\n                12,\n                FontWeight.w500,\n              );\n              break;\n            case BTTableCellType.badge:\n              w = measureText(\n                    cell.badgeLabel ?? cell.label ?? 'Badge',\n                    11,\n                    FontWeight.w500,\n                  ) +\n                  24; // badge pill padding\n              break;\n            case BTTableCellType.button:\n              w = measureText(cell.label ?? 'Label', 12, FontWeight.w500) + 24;\n              break;\n            case BTTableCellType.doubleButton:\n              w = 72; // two 32px iconOnly buttons + 4 gap + padding\n              break;\n            case BTTableCellType.checkbox:\n            case BTTableCellType.radio:\n            case BTTableCellType.toggle:\n              w = 32;\n              break;\n            case BTTableCellType.option:\n              w = 180; // two radios + labels\n              break;\n            case BTTableCellType.field:\n            case BTTableCellType.dropdown:\n              w = 160; // input min width\n              break;\n            case BTTableCellType.multipleSelection:\n              w = 220;\n              break;\n          }\n        } else if (raw != null) {\n          w = measureText(raw.toString(), 12, FontWeight.w500);\n        }\n\n        // Tree expander indent — accumulates with depth.\n        // depth >= 1 → indent = 4 + (depth-1)*24; depth=0 (defensive) → 0.\n        if (col.expander) {\n          final indent = depth >= 1 ? 4.0 + (depth - 1) * 24.0 : 0.0;\n          w += indent + 16 /* chevron/leaf */ + 4 /* gap before content */;\n        }\n\n        if (w > maxContentW) maxContentW = w;\n\n        // Only recurse into children if the row is currently expanded.\n        // Collapsed rows hide their subtree, so they shouldn't count.\n        final isExpanded = widget.expandedKeys[row.id] == true;\n        if (isExpanded && row.children != null) {\n          traverse(row.children!, depth + 1);\n        }\n      }\n    }\n\n    // BTTableRow renders top-level rows with depth=1 (matches its _buildRows call)\n    traverse(widget.rows, 1);\n\n    return (maxContentW + padding).clamp(minWidth, maxWidth);\n  }\n\n  // ── Check-all logic ────────────────────────────────────────────────────────\n\n  /// Header tri-state — derived from each top-level row's recursive check state,\n  /// NOT from flat IDs. A parent row counts as \"checked\" when all its leaf\n  /// descendants are selected, even if the parent's own ID isn't in selectedRows.\n  /// Mirrors web computeHeaderCheckState logic.\n  bool? get _checkAllState {\n    if (widget.rows.isEmpty) return false;\n    final sel = widget.selectedRows;\n    final states = widget.rows.map((r) => _rowCheckState(r, sel)).toList();\n    if (states.every((s) => s == true)) return true;\n    if (states.every((s) => s == false)) return false;\n    return null; // indeterminate\n  }\n\n  /// Recursive tri-state for a single row — mirrors BTTableRow._computeParentCheckState.\n  /// Leaf row: true iff its id is in `sel`.\n  /// Parent row: derived from children's states (all true → true, all false → false,\n  /// mixed → null/indeterminate).\n  static bool? _rowCheckState(BTDataTableRow row, List<String> sel) {\n    if (row.children == null || row.children!.isEmpty) {\n      return sel.contains(row.id);\n    }\n    final childStates =\n        row.children!.map((c) => _rowCheckState(c, sel)).toList();\n    if (childStates.every((s) => s == true)) return true;\n    if (childStates.every((s) => s == false)) return false;\n    return null;\n  }\n\n  static List<String> _allRowIds(List<BTDataTableRow> rows) {\n    final result = <String>[];\n    for (final r in rows) {\n      result.add(r.id);\n      if (r.children != null) {\n        result.addAll(_allRowIds(r.children!));\n      }\n    }\n    return result;\n  }\n\n  void _handleCheckAll() {\n    final allIds = _allRowIds(widget.rows);\n    final current = _checkAllState;\n    final List<String> next;\n    if (current == true) {\n      next = [];\n    } else {\n      next = allIds;\n    }\n    widget.onSelectedRowsChanged?.call(next);\n    widget.onAction?.call(\n      const BTTableActionPayload(action: 'check-all'),\n    );\n  }\n\n  void _handleCheckRow(String rowId) {\n    // Find the clicked row and cascade to all its descendants — matches web logic.\n    final target = _findRow(widget.rows, rowId);\n    final affectedIds = target != null ? _allRowIds([target]) : [rowId];\n\n    final sel = List<String>.from(widget.selectedRows);\n    final allSelected = affectedIds.every(sel.contains);\n\n    if (allSelected) {\n      sel.removeWhere(affectedIds.contains);\n    } else {\n      for (final id in affectedIds) {\n        if (!sel.contains(id)) sel.add(id);\n      }\n    }\n\n    widget.onSelectedRowsChanged?.call(sel);\n    widget.onAction?.call(\n      BTTableActionPayload(action: 'check-row', rowId: rowId),\n    );\n  }\n\n  static BTDataTableRow? _findRow(List<BTDataTableRow> rows, String id) {\n    for (final r in rows) {\n      if (r.id == id) return r;\n      if (r.children != null) {\n        final found = _findRow(r.children!, id);\n        if (found != null) return found;\n      }\n    }\n    return null;\n  }\n\n  static List<_VisibleDataTableRow> _flattenVisibleRows(\n    List<BTDataTableRow> rows,\n    Map<String, bool> expandedKeys, [\n    int depth = 1,\n  ]) {\n    final visible = <_VisibleDataTableRow>[];\n    for (final row in rows) {\n      visible.add(_VisibleDataTableRow(row: row, depth: depth));\n      final children = row.children;\n      if (children != null &&\n          children.isNotEmpty &&\n          expandedKeys[row.id] == true) {\n        visible.addAll(_flattenVisibleRows(children, expandedKeys, depth + 1));\n      }\n    }\n    return visible;\n  }\n\n  // ── Sort ───────────────────────────────────────────────────────────────────\n\n  void _handleSort(String key, BTDataTableSortDirection current) {\n    final next = switch (current) {\n      BTDataTableSortDirection.none => BTDataTableSortDirection.asc,\n      BTDataTableSortDirection.asc => BTDataTableSortDirection.desc,\n      BTDataTableSortDirection.desc => BTDataTableSortDirection.none,\n    };\n    widget.onSortChanged?.call(BTSortPayload(columnKey: key, direction: next));\n  }\n\n  // ── Build ──────────────────────────────────────────────────────────────────\n\n  @override\n  Widget build(BuildContext context) {\n    final c = context.btColor;\n\n    return Column(\n      mainAxisSize: MainAxisSize.min,\n      crossAxisAlignment: CrossAxisAlignment.stretch,\n      children: [\n        // ── Toolbar ────────────────────────────────────────────────────────\n        if (widget.showToolbar) _buildToolbar(context, c),\n\n        // ── Filter tags ────────────────────────────────────────────────────\n        if (widget.showFilter && widget.filters.isNotEmpty)\n          _buildFilters(context, c),\n\n        // ── Table — LayoutBuilder gives the actual container width\n        //   synchronously per frame. No floor, no 2-frame delay, no overflow\n        //   when container < previously-cached size.\n        LayoutBuilder(\n          builder: (context, constraints) {\n            final viewportWidth = constraints.maxWidth;\n            final colWidths = _computeColumnWidths(viewportWidth);\n            return _buildTableFrame(context, c, colWidths, viewportWidth);\n          },\n        ),\n\n        // ── Pagination ─────────────────────────────────────────────────────\n        if (widget.showPagination) _buildPagination(context, c),\n      ],\n    );\n  }\n\n  // ── Toolbar ────────────────────────────────────────────────────────────────\n\n  /// Header layout (Figma 4001-62044):\n  ///   Row 1: Title\n  ///   Row 2: Full-width search input\n  ///   Row 3: Filter button + toolbar actions (Download/Upload/Create)\n  Widget _buildToolbar(BuildContext context, BTColorTheme c) {\n    final activeFilterCount = widget.filters.length;\n    final filterButton = BTButton.iconOnly(\n      icon: Icon(\n        Icons.filter_alt,\n        size: 16,\n        color: c.text.primary,\n      ),\n      variant: BTButtonVariant.secondaryWhite,\n      size: BTButtonSize.md,\n      rightIcon: activeFilterCount > 0\n          ? BTHint(count: activeFilterCount, size: BTHintSize.sm)\n          : null,\n      onPressed: () => widget.onAction?.call(\n        const BTTableActionPayload(action: 'filter'),\n      ),\n    );\n\n    final defaultActions = Row(\n      mainAxisSize: MainAxisSize.min,\n      children: [\n        BTButton(\n          label: 'Download',\n          leftIcon: Icon(\n            Icons.download_rounded,\n            size: 16,\n            color: c.text.secondary,\n          ),\n          variant: BTButtonVariant.secondaryWhite,\n          size: BTButtonSize.md,\n          onPressed: () => widget.onAction?.call(\n            const BTTableActionPayload(action: 'download'),\n          ),\n        ),\n        const SizedBox(width: 8.0),\n        BTButton(\n          label: 'Upload',\n          leftIcon: Icon(\n            Icons.upload_rounded,\n            size: 16,\n            color: c.text.secondary,\n          ),\n          variant: BTButtonVariant.secondaryWhite,\n          size: BTButtonSize.md,\n          onPressed: () => widget.onAction?.call(\n            const BTTableActionPayload(action: 'upload'),\n          ),\n        ),\n        const SizedBox(width: 8.0),\n        BTButton(\n          label: '+ Create',\n          variant: BTButtonVariant.primary,\n          size: BTButtonSize.md,\n          onPressed: () => widget.onAction?.call(\n            const BTTableActionPayload(action: 'create'),\n          ),\n        ),\n      ],\n    );\n\n    final actionContent = Row(\n      mainAxisSize: MainAxisSize.min,\n      children: [\n        if (widget.showFilter) ...[\n          filterButton,\n          const SizedBox(width: 8.0),\n        ],\n        widget.toolbarActions ?? defaultActions,\n      ],\n    );\n\n    return Padding(\n      padding: const EdgeInsets.only(bottom: 8.0),\n      child: Column(\n        mainAxisSize: MainAxisSize.min,\n        crossAxisAlignment: CrossAxisAlignment.stretch,\n        children: [\n          // ── Row 1: Title ─────────────────────────────────────────────────\n          Padding(\n            padding: const EdgeInsets.only(bottom: 8.0),\n            child: Text(\n              widget.title,\n              style: TextStyle(\n                fontFamily: BTTypography.fontFamily,\n                fontSize: 14.0,\n                fontWeight: FontWeight.w600,\n                color: c.text.primary,\n              ),\n            ),\n          ),\n\n          // ── Row 2: Full-width search ─────────────────────────────────────\n          if (widget.showSearch)\n            Padding(\n              padding: const EdgeInsets.only(bottom: 8.0),\n              child: BTInputSearch(\n                value: widget.searchValue,\n                placeholder: 'Search',\n                onChanged: widget.onSearchValueChanged,\n                onSearch: widget.onSearchSubmit,\n              ),\n            ),\n\n          // ── Row 3: Filter + action buttons (right-aligned) ───────────────\n          LayoutBuilder(\n            builder: (context, constraints) {\n              final isCompact = constraints.maxWidth < 520;\n\n              if (isCompact) {\n                return SingleChildScrollView(\n                  scrollDirection: Axis.horizontal,\n                  physics: const ClampingScrollPhysics(),\n                  child: actionContent,\n                );\n              }\n\n              return Row(\n                crossAxisAlignment: CrossAxisAlignment.center,\n                children: [\n                  const Spacer(),\n                  actionContent,\n                ],\n              );\n            },\n          ),\n        ],\n      ),\n    );\n  }\n\n  // ── Filter tags ────────────────────────────────────────────────────────────\n\n  Widget _buildFilters(BuildContext context, BTColorTheme c) {\n    final visible = widget.filters.take(widget.maxVisibleFilters).toList();\n    final hidden = widget.filters.skip(widget.maxVisibleFilters).toList();\n\n    return Container(\n      margin: const EdgeInsets.only(bottom: 8.0),\n      child: Wrap(\n        spacing: 8.0,\n        runSpacing: 4.0,\n        crossAxisAlignment: WrapCrossAlignment.center,\n        children: [\n          for (final tag in visible)\n            BTTag(\n              label: tag,\n              onRemove: () => widget.onRemoveFilter?.call(tag),\n            ),\n          // \"+N\" overflow → BTDropdown listing hidden filter tags. Each row\n          // shows an × icon on the right (space-between via removable: true)\n          // signalling that tapping the row will remove that filter.\n          if (hidden.isNotEmpty)\n            BTDropdown<String>(\n              items: [\n                for (final tag in hidden)\n                  BTDropdownItem<String>(\n                    value: tag,\n                    label: tag,\n                    removable: true,\n                  ),\n              ],\n              onSelect: (tag) {\n                if (tag != null) widget.onRemoveFilter?.call(tag);\n              },\n              trigger: ({required toggle, required isOpen}) => GestureDetector(\n                onTap: toggle,\n                behavior: HitTestBehavior.opaque,\n                child: BTTag(label: '+${hidden.length}'),\n              ),\n            ),\n          if (widget.filters.isNotEmpty)\n            BTButtonLink.secondary(\n              label: 'Remove All',\n              onPressed: widget.onRemoveAllFilters,\n            ),\n        ],\n      ),\n    );\n  }\n\n  // ── Table frame ────────────────────────────────────────────────────────────\n\n  Widget _buildTableFrame(\n    BuildContext context,\n    BTColorTheme c,\n    List<double> colWidths,\n    double containerWidth,\n  ) {\n    final bg = switch (widget.variant) {\n      BTDataTableVariant.noFill => Colors.transparent,\n      _ => c.bg.primary,\n    };\n\n    // ── Responsive degrade: when the container is too narrow to fit\n    // (left fixed + right fixed + a minimal middle viewport), disable sticky\n    // columns entirely so the whole table scrolls horizontally. Prevents the\n    // RenderFlex overflow stripes on phones in portrait orientation.\n    const borderInset = 2.0;\n    const minMiddleViewport = 80.0; // smallest \"scrollable middle\" we'll allow\n\n    int effectiveLeft = widget.fixedLeft.clamp(0, widget.columns.length);\n    int effectiveRight =\n        widget.fixedRight.clamp(0, widget.columns.length - effectiveLeft);\n\n    final checkboxW = widget.hasCheckbox ? kCheckboxWidth : 0.0;\n    double leftColsWTest =\n        colWidths.sublist(0, effectiveLeft).fold(0.0, (a, b) => a + b);\n    double rightColsWTest = effectiveRight > 0\n        ? colWidths\n            .sublist(widget.columns.length - effectiveRight)\n            .fold(0.0, (a, b) => a + b)\n        : 0.0;\n\n    final canFitSticky = (checkboxW +\n            leftColsWTest +\n            rightColsWTest +\n            borderInset +\n            minMiddleViewport) <=\n        containerWidth;\n    if (!canFitSticky) {\n      effectiveLeft = 0;\n      effectiveRight = 0;\n    }\n\n    // Column split indices (using possibly-zeroed effective counts)\n    final leftCount = effectiveLeft;\n    final rightCount = effectiveRight;\n    final middleEnd = widget.columns.length - rightCount;\n\n    // Pixel widths\n    final leftColsW =\n        colWidths.sublist(0, leftCount).fold(0.0, (a, b) => a + b);\n    final rightColsW = rightCount > 0\n        ? colWidths.sublist(middleEnd).fold(0.0, (a, b) => a + b)\n        : 0.0;\n    final leftW = checkboxW + leftColsW;\n    final middleColsW =\n        colWidths.sublist(leftCount, middleEnd).fold(0.0, (a, b) => a + b);\n\n    final availableMiddle = max(\n      0.0,\n      containerWidth - leftW - rightColsW - borderInset,\n    );\n\n    // Table fits container → visibleMiddleW = middleColsW (don't stretch),\n    // total table width = sum of all column widths.\n    // Table overflows → visibleMiddleW = available viewport (scroll horizontally).\n    final fits = middleColsW <= availableMiddle;\n    final visibleMiddleW = fits ? middleColsW : availableMiddle;\n    final middleW = max(middleColsW, visibleMiddleW);\n\n    final tableBody = _buildTableBody(\n      context,\n      c,\n      colWidths,\n      leftCount,\n      rightCount,\n      middleW,\n      visibleMiddleW,\n    );\n\n    // Horizontal-scroll shadow indicators (hoisted from per-row to here).\n    // One ValueListenableBuilder for the entire table → spans the full\n    // table height (header + all data rows) via Positioned.fill.\n    final hasLeftSection = widget.hasCheckbox || leftCount > 0;\n    final hasRightSection = rightCount > 0;\n    final maxHScroll =\n        middleW > visibleMiddleW ? middleW - visibleMiddleW : 0.0;\n\n    final tableFrame = Container(\n      decoration: BoxDecoration(\n        color: bg,\n        border: Border.all(color: c.border.primary),\n        borderRadius: BorderRadius.circular(8.0),\n      ),\n      child: ClipRRect(\n        borderRadius: BorderRadius.circular(8.0),\n        child: Stack(\n          children: [\n            tableBody,\n            if (hasLeftSection || hasRightSection)\n              Positioned.fill(\n                child: IgnorePointer(\n                  child: ValueListenableBuilder<double>(\n                    valueListenable: _hScrollOffset,\n                    builder: (ctx, offset, _) {\n                      final showLeading = hasLeftSection && offset > 0.5;\n                      final showTrailing = hasRightSection &&\n                          maxHScroll > 0.5 &&\n                          offset < maxHScroll - 0.5;\n                      if (!showLeading && !showTrailing) {\n                        return const SizedBox.shrink();\n                      }\n                      return _BTTableShadowOverlay(\n                        leftWidth: leftW,\n                        rightWidth: rightColsW,\n                        showLeading: showLeading,\n                        showTrailing: showTrailing,\n                      );\n                    },\n                  ),\n                ),\n              ),\n          ],\n        ),\n      ),\n    );\n\n    // When content fits container, align table to the start so it sizes to\n    // content (instead of stretching to full container width via Column.stretch).\n    if (fits) {\n      final totalTableW = leftW + visibleMiddleW + rightColsW + borderInset;\n      return Align(\n        alignment: Alignment.centerLeft,\n        child: SizedBox(width: totalTableW, child: tableFrame),\n      );\n    }\n    return tableFrame;\n  }\n\n  // ── Table body (header + rows) ─────────────────────────────────────────────\n\n  Widget _buildTableBody(\n    BuildContext context,\n    BTColorTheme c,\n    List<double> colWidths,\n    int leftCount,\n    int rightCount,\n    double middleW,\n    double visibleMiddleW,\n  ) {\n    final header = BTTableTitle(\n      columns: widget.columns,\n      variant: widget.variant,\n      hasCheckbox: widget.hasCheckbox,\n      checkAllState: _checkAllState,\n      columnWidths: colWidths,\n      fixedLeft: leftCount,\n      fixedRight: rightCount,\n      hScrollOffset: _hScrollOffset,\n      onHorizontalOffsetChanged: (offset) => _hScrollOffset.value = offset,\n      middleW: middleW,\n      visibleMiddleW: visibleMiddleW,\n      headerMinHeight: widget.headerMinHeight,\n      onCheckAll: widget.hasCheckbox ? _handleCheckAll : null,\n      onSort: _handleSort,\n    );\n\n    final divider = Container(height: 1.0, color: c.border.primary);\n    final visibleRows = _flattenVisibleRows(widget.rows, widget.expandedKeys);\n    final maxHorizontalOffset =\n        middleW > visibleMiddleW ? middleW - visibleMiddleW : 0.0;\n    final estimatedBodyHeight = visibleRows.isEmpty\n        ? 0.0\n        : visibleRows.length * widget.rowMinHeight +\n            max(0, visibleRows.length - 1).toDouble();\n    final estimatedHeaderHeight = widget.headerMinHeight + 1.0;\n\n    Widget buildRowAt(int index) {\n      final visibleRow = visibleRows[index];\n      return BTTableRow(\n        key: ValueKey(visibleRow.row.id),\n        row: visibleRow.row,\n        columns: widget.columns,\n        columnWidths: colWidths,\n        depth: visibleRow.depth,\n        variant: widget.variant,\n        hasCheckbox: widget.hasCheckbox,\n        isSelected: widget.selectedRows.contains(visibleRow.row.id),\n        expandedKeys: widget.expandedKeys,\n        selectedRows: widget.selectedRows,\n        fixedLeft: leftCount,\n        fixedRight: rightCount,\n        hScrollOffset: _hScrollOffset,\n        onHorizontalOffsetChanged: (offset) {\n          _hScrollOffset.value = offset;\n        },\n        middleW: middleW,\n        visibleMiddleW: visibleMiddleW,\n        rowMinHeight: widget.rowMinHeight,\n        showBottomDivider: index != visibleRows.length - 1,\n        onCheckRow: widget.hasCheckbox ? _handleCheckRow : null,\n        onCellChange: widget.onCellChange,\n        onExpandedKeysChanged: widget.onExpandedKeysChanged,\n      );\n    }\n\n    final rows = Column(\n      mainAxisSize: MainAxisSize.min,\n      crossAxisAlignment: CrossAxisAlignment.stretch,\n      children: List.generate(visibleRows.length, buildRowAt),\n    );\n\n    final isRtl = Directionality.of(context) == TextDirection.rtl;\n    final dragSign = isRtl ? 1.0 : -1.0;\n\n    final bodyContent = GestureDetector(\n      behavior: HitTestBehavior.translucent,\n      onHorizontalDragUpdate: maxHorizontalOffset <= 0\n          ? null\n          : (details) {\n              final next = (_hScrollOffset.value + dragSign * details.delta.dx)\n                  .clamp(0.0, maxHorizontalOffset);\n              if ((next - _hScrollOffset.value).abs() >= 0.5) {\n                _hScrollOffset.value = next;\n              }\n            },\n      child: rows,\n    );\n\n    final lazyBodyContent = GestureDetector(\n      behavior: HitTestBehavior.translucent,\n      onHorizontalDragUpdate: maxHorizontalOffset <= 0\n          ? null\n          : (details) {\n              final next = (_hScrollOffset.value + dragSign * details.delta.dx)\n                  .clamp(0.0, maxHorizontalOffset);\n              if ((next - _hScrollOffset.value).abs() >= 0.5) {\n                _hScrollOffset.value = next;\n              }\n            },\n      child: ListView.builder(\n        controller: _vScrollCtrl,\n        physics: const ClampingScrollPhysics(),\n        itemCount: visibleRows.length,\n        cacheExtent: widget.rowMinHeight * 8,\n        itemBuilder: (context, index) => buildRowAt(index),\n      ),\n    );\n\n    if (widget.maxHeight == null) {\n      return Column(\n        mainAxisSize: MainAxisSize.min,\n        crossAxisAlignment: CrossAxisAlignment.stretch,\n        children: [header, divider, bodyContent],\n      );\n    }\n\n    if (widget.fixedHeader) {\n      final bodyHeight = min(\n        widget.maxHeight!,\n        estimatedBodyHeight <= 0 ? widget.rowMinHeight : estimatedBodyHeight,\n      );\n\n      return Column(\n        mainAxisSize: MainAxisSize.min,\n        crossAxisAlignment: CrossAxisAlignment.stretch,\n        children: [\n          header,\n          divider,\n          SizedBox(\n            height: bodyHeight,\n            child: lazyBodyContent,\n          ),\n        ],\n      );\n    }\n\n    final tableHeight = min(\n      widget.maxHeight!,\n      estimatedHeaderHeight +\n          (estimatedBodyHeight <= 0\n              ? widget.rowMinHeight\n              : estimatedBodyHeight),\n    );\n\n    return SizedBox(\n      height: tableHeight,\n      child: SingleChildScrollView(\n        controller: _vScrollCtrl,\n        physics: const ClampingScrollPhysics(),\n        child: Column(\n          mainAxisSize: MainAxisSize.min,\n          crossAxisAlignment: CrossAxisAlignment.stretch,\n          children: [header, divider, bodyContent],\n        ),\n      ),\n    );\n  }\n\n  // ── Pagination ─────────────────────────────────────────────────────────────\n\n  Widget _buildPagination(BuildContext context, BTColorTheme c) {\n    return Container(\n      margin: const EdgeInsets.only(top: 8.0),\n      child: BTPagination.display(\n        currentPage: widget.currentPage,\n        totalPages: widget.totalPages,\n        totalCount: widget.rows.length,\n        rowsPerPage: widget.rowsPerPage,\n        rowsPerPageOptions: widget.rowsPerPageOptions,\n        onPageChange: widget.onPageChange ?? (_) {},\n        onRowsChange: widget.onRowsChange,\n      ),\n    );\n  }\n}\n\nclass _VisibleDataTableRow {\n  const _VisibleDataTableRow({\n    required this.row,\n    required this.depth,\n  });\n\n  final BTDataTableRow row;\n  final int depth;\n}\n\n/// Table-level horizontal-scroll shadow overlay. Renders 18px linear-gradient\n/// bands at the inner edge of the left/right sticky sections to indicate that\n/// more content exists past the pinned column. Hoisted from per-row to here\n/// so the gradient spans the full table height (header + all data rows) and\n/// only ONE ValueListenableBuilder rebuilds on each horizontal scroll tick.\nclass _BTTableShadowOverlay extends StatelessWidget {\n  const _BTTableShadowOverlay({\n    required this.leftWidth,\n    required this.rightWidth,\n    required this.showLeading,\n    required this.showTrailing,\n  });\n\n  final double leftWidth;\n  final double rightWidth;\n  final bool showLeading;\n  final bool showTrailing;\n\n  @override\n  Widget build(BuildContext context) {\n    const shadowWidth = 18.0;\n\n    return Stack(\n      clipBehavior: Clip.none,\n      children: [\n        if (showLeading)\n          PositionedDirectional(\n            top: 0,\n            bottom: 0,\n            start: leftWidth,\n            width: shadowWidth,\n            child: const DecoratedBox(\n              decoration: BoxDecoration(\n                gradient: LinearGradient(\n                  begin: AlignmentDirectional.centerStart,\n                  end: AlignmentDirectional.centerEnd,\n                  colors: [\n                    Color(0x14000000),\n                    Color(0x0A000000),\n                    Color(0x00000000),\n                  ],\n                ),\n              ),\n            ),\n          ),\n        if (showTrailing)\n          PositionedDirectional(\n            top: 0,\n            bottom: 0,\n            end: rightWidth,\n            width: shadowWidth,\n            child: const DecoratedBox(\n              decoration: BoxDecoration(\n                gradient: LinearGradient(\n                  begin: AlignmentDirectional.centerEnd,\n                  end: AlignmentDirectional.centerStart,\n                  colors: [\n                    Color(0x14000000),\n                    Color(0x0A000000),\n                    Color(0x00000000),\n                  ],\n                ),\n              ),\n            ),\n          ),\n      ],\n    );\n  }\n}\n"
    },
    {
      "path": "internal/bt_synced_horizontal_viewport.dart",
      "target": "@flutterBase/data-table/internal/bt_synced_horizontal_viewport.dart",
      "type": "registry:ui",
      "content": "import 'package:flutter/foundation.dart';\nimport 'package:flutter/material.dart';\n\nclass BTSyncedHorizontalViewport extends StatefulWidget {\n  const BTSyncedHorizontalViewport({\n    required this.offsetListenable,\n    required this.onOffsetChanged,\n    required this.viewportWidth,\n    required this.contentWidth,\n    required this.child,\n    this.interactive = true,\n    super.key,\n  });\n\n  final ValueListenable<double> offsetListenable;\n  final ValueChanged<double> onOffsetChanged;\n  final double viewportWidth;\n  final double contentWidth;\n  final Widget child;\n  final bool interactive;\n\n  @override\n  State<BTSyncedHorizontalViewport> createState() =>\n      _BTSyncedHorizontalViewportState();\n}\n\nclass _BTSyncedHorizontalViewportState\n    extends State<BTSyncedHorizontalViewport> {\n  ScrollController? _controller;\n  bool _isSyncing = false;\n\n  @override\n  void initState() {\n    super.initState();\n    _attachController();\n  }\n\n  @override\n  void didUpdateWidget(covariant BTSyncedHorizontalViewport oldWidget) {\n    super.didUpdateWidget(oldWidget);\n    if (oldWidget.offsetListenable != widget.offsetListenable) {\n      oldWidget.offsetListenable.removeListener(_syncFromExternalOffset);\n      widget.offsetListenable.addListener(_syncFromExternalOffset);\n    }\n    WidgetsBinding.instance.addPostFrameCallback((_) {\n      if (mounted) _syncFromExternalOffset();\n    });\n  }\n\n  @override\n  void dispose() {\n    _detachController();\n    super.dispose();\n  }\n\n  void _attachController() {\n    if (_controller != null) return;\n    final controller = ScrollController();\n    controller.addListener(_handleScroll);\n    widget.offsetListenable.addListener(_syncFromExternalOffset);\n    _controller = controller;\n  }\n\n  void _detachController() {\n    final controller = _controller;\n    if (controller == null) return;\n    widget.offsetListenable.removeListener(_syncFromExternalOffset);\n    controller.removeListener(_handleScroll);\n    controller.dispose();\n    _controller = null;\n  }\n\n  void _handleScroll() {\n    final controller = _controller;\n    if (_isSyncing || controller == null || !controller.hasClients) return;\n    widget.onOffsetChanged(controller.offset);\n  }\n\n  void _syncFromExternalOffset() {\n    final controller = _controller;\n    if (controller == null || !controller.hasClients) return;\n    final target = widget.offsetListenable.value.clamp(\n      0.0,\n      controller.position.maxScrollExtent,\n    );\n    if ((controller.offset - target).abs() < 0.5) return;\n    _isSyncing = true;\n    controller.jumpTo(target);\n    _isSyncing = false;\n  }\n\n  @override\n  Widget build(BuildContext context) {\n    final viewportWidth = widget.viewportWidth.clamp(0.0, double.infinity);\n    final contentWidth = widget.contentWidth < viewportWidth\n        ? viewportWidth\n        : widget.contentWidth;\n\n    return SizedBox(\n      width: viewportWidth,\n      child: SingleChildScrollView(\n        controller: _controller,\n        scrollDirection: Axis.horizontal,\n        physics: widget.interactive\n            ? const ClampingScrollPhysics()\n            : const NeverScrollableScrollPhysics(),\n        child: SizedBox(\n          width: contentWidth,\n          child: widget.child,\n        ),\n      ),\n    );\n  }\n}\n"
    },
    {
      "path": "internal/bt_table_item.dart",
      "target": "@flutterBase/data-table/internal/bt_table_item.dart",
      "type": "registry:ui",
      "content": "// internal — single cell renderer for BTDataTable (not exported)\nimport 'package:btech_tokens/btech_tokens.dart';\nimport '../../badge/badge.types.dart';\nimport '../../badge/badge.widget.dart';\nimport '../../button/button.types.dart';\nimport '../../button/button.widget.dart';\nimport '../../checkbox/checkbox.widget.dart';\nimport '../../dropdown-list/dropdown_list.types.dart';\nimport '../../radio-button/radio_button.widget.dart';\nimport '../../switch-field/switch_field.types.dart';\nimport '../../switch-field/switch_field.widget.dart';\nimport '../../input/dropdown/input_dropdown.widget.dart';\nimport '../../input/input.widget.dart';\nimport '../../input/multiple_field/input_multiple_field.widget.dart';\nimport 'package:btech_ui/src/components/organisms/data_table/bt_data_table.types.dart';\nimport 'package:flutter/material.dart';\nimport 'package:flutter_svg/flutter_svg.dart';\n\n// ─── Inline SVG icons matching the web double-button design ──────────────────\nconst _kEditSvg =\n    '''\n<svg viewBox=\"0 0 16 16\" xmlns=\"http://www.w3.org/2000/svg\">\n  <path d=\"M3 8.67V12.5H6.83L12.13 7.2L8.3 3.37L3 8.67Z\n           M13.03 6.3L13.75 5.58C14.08 5.25 14.08 4.73 13.75 4.4\n           L11.6 2.25C11.27 1.92 10.75 1.92 10.42 2.25L9.7 2.97L13.03 6.3Z\"\n        fill=\"black\"/>\n</svg>''';\n\nconst _kListSvg =\n    '''\n<svg viewBox=\"0 0 16 16\" xmlns=\"http://www.w3.org/2000/svg\">\n  <path d=\"M3.5 4.5H12.5V5.83H3.5V4.5Z\n           M3.5 7.33H12.5V8.67H3.5V7.33Z\n           M3.5 10.17H12.5V11.5H3.5V10.17Z\"\n        fill=\"black\"/>\n</svg>''';\n\n/// Renders the content of a single data cell.\n///\n/// All interactive cells delegate to `onCellChange` — the parent table\n/// owns mutable state; this widget is stateless for everything except the\n/// text-field controller which must persist across rebuilds.\nclass BTTableItem extends StatefulWidget {\n  const BTTableItem({\n    required this.column,\n    required this.rowId,\n    required this.cell,\n    this.onCellChange,\n    super.key,\n  });\n\n  final BTDataTableColumn column;\n  final String rowId;\n  final BTDataTableCell cell;\n  final void Function(BTDataTableCellChangePayload)? onCellChange;\n\n  @override\n  State<BTTableItem> createState() => _BTTableItemState();\n}\n\nclass _BTTableItemState extends State<BTTableItem> {\n  // Field controller persists across rebuilds so text is not lost.\n  late final TextEditingController _fieldCtrl;\n\n  @override\n  void initState() {\n    super.initState();\n    _fieldCtrl = TextEditingController(\n      text: widget.cell.value?.toString() ?? '',\n    );\n  }\n\n  @override\n  void dispose() {\n    _fieldCtrl.dispose();\n    super.dispose();\n  }\n\n  void _emit(BTDataTableCell updated) {\n    widget.onCellChange?.call(\n      BTDataTableCellChangePayload(\n        rowId: widget.rowId,\n        columnKey: widget.column.key,\n        cell: updated,\n      ),\n    );\n  }\n\n  @override\n  Widget build(BuildContext context) {\n    final c = context.btColor;\n    final cell = widget.cell;\n    final align = switch (widget.column.align) {\n      BTDataTableColumnAlign.center => Alignment.center,\n      BTDataTableColumnAlign.end => Alignment.centerRight,\n      BTDataTableColumnAlign.start => Alignment.centerLeft,\n    };\n\n    // Sections wrapped in IntrinsicHeight auto-expand to tallest content.\n    // No fixed height — field/dropdown cells (BTInput = 50dp) size naturally.\n    return Align(\n      alignment: align,\n      child: switch (cell.type) {\n        BTTableCellType.text => _padded(_text(c, cell)),\n        BTTableCellType.number => _padded(_number(c, cell)),\n        BTTableCellType.button => _padded(_button(cell)),\n        BTTableCellType.doubleButton => _padded(_doubleButton(c, cell)),\n        BTTableCellType.checkbox => _padded(_checkbox(cell)),\n        BTTableCellType.radio => _padded(_radio(cell)),\n        BTTableCellType.option => _padded(_BTTableOption(\n            cell: cell,\n            onChanged: (v) => _emit(\n              BTDataTableCell(\n                type: BTTableCellType.option,\n                value: v,\n                options: cell.options,\n                disabled: cell.disabled,\n              ),\n            ),\n          )),\n        BTTableCellType.field => _fieldCell(cell),\n        BTTableCellType.dropdown => _dropdownCell(cell),\n        BTTableCellType.multipleSelection => _multipleSelectionCell(cell),\n        BTTableCellType.badge => _padded(_badge(cell)),\n        BTTableCellType.toggle => _padded(_toggle(cell)),\n      },\n    );\n  }\n\n  // ── Helpers ─────────────────────────────────────────────────────────────────\n\n  Widget _padded(Widget child) => child;\n\n  // ── text ────────────────────────────────────────────────────────────────────\n\n  Widget _text(BTColorTheme c, BTDataTableCell cell) => Text(\n        cell.value?.toString() ?? '',\n        style: TextStyle(\n          fontFamily: BTTypography.fontFamily,\n          fontSize: 12,\n          fontWeight: FontWeight.w500,\n          height: 16 / 12,\n          color: c.text.primary,\n        ),\n        overflow: TextOverflow.ellipsis,\n      );\n\n  // ── number ──────────────────────────────────────────────────────────────────\n\n  Widget _number(BTColorTheme c, BTDataTableCell cell) => Text(\n        cell.value?.toString() ?? '',\n        textAlign: TextAlign.end,\n        style: TextStyle(\n          fontFamily: BTTypography.fontFamily,\n          fontSize: 12,\n          fontWeight: FontWeight.w500,\n          height: 16 / 12,\n          color: c.text.primary,\n        ),\n      );\n\n  // ── button ──────────────────────────────────────────────────────────────────\n\n  /// Renders a single [BTButton] (primary variant, sm size).\n  Widget _button(BTDataTableCell cell) => BTButton(\n        label: cell.label ?? 'Label',\n        variant: BTButtonVariant.primary,\n        size: BTButtonSize.sm,\n        onPressed: cell.disabled ? null : () => _emit(cell),\n      );\n\n  // ── double-button ────────────────────────────────────────────────────────────\n\n  /// Two [BTButton.iconOnly] widgets side-by-side — an edit (primary) and a\n  /// menu/list (secondary-light) action.  Icons match the web SVG paths.\n  Widget _doubleButton(BTColorTheme c, BTDataTableCell cell) => Row(\n        mainAxisSize: MainAxisSize.min,\n        children: [\n          // Primary — edit action\n          BTButton.iconOnly(\n            icon: SvgPicture.string(\n              _kEditSvg,\n              width: 14,\n              height: 14,\n              colorFilter: ColorFilter.mode(c.text.inverse, BlendMode.srcIn),\n            ),\n            variant: BTButtonVariant.primary,\n            size: BTButtonSize.sm,\n            onPressed: cell.disabled\n                ? null\n                : () => _emit(\n                      BTDataTableCell(\n                        type: BTTableCellType.doubleButton,\n                        value: 'edit',\n                        label: cell.label,\n                        disabled: cell.disabled,\n                      ),\n                    ),\n          ),\n          const SizedBox(width: 4),\n          // Secondary — list/menu action\n          BTButton.iconOnly(\n            icon: SvgPicture.string(\n              _kListSvg,\n              width: 14,\n              height: 14,\n              colorFilter: ColorFilter.mode(c.text.secondary, BlendMode.srcIn),\n            ),\n            variant: BTButtonVariant.secondaryLight,\n            size: BTButtonSize.sm,\n            onPressed: cell.disabled\n                ? null\n                : () => _emit(\n                      BTDataTableCell(\n                        type: BTTableCellType.doubleButton,\n                        value: 'list',\n                        label: cell.label,\n                        disabled: cell.disabled,\n                      ),\n                    ),\n          ),\n        ],\n      );\n\n  // ── checkbox ─────────────────────────────────────────────────────────────────\n\n  Widget _checkbox(BTDataTableCell cell) => BTCheckbox(\n        checked: cell.checked,\n        disabled: cell.disabled,\n        onChanged: cell.disabled\n            ? null\n            : (_) => _emit(\n                  BTDataTableCell(\n                    type: BTTableCellType.checkbox,\n                    checked: !cell.checked,\n                    disabled: cell.disabled,\n                  ),\n                ),\n      );\n\n  // ── radio ─────────────────────────────────────────────────────────────────────\n\n  Widget _radio(BTDataTableCell cell) => BTRadioButton<bool>(\n        groupValue: cell.selected,\n        value: true,\n        disabled: cell.disabled,\n        // onChanged is required non-nullable; the disabled flag suppresses taps.\n        onChanged: (_) => _emit(\n          BTDataTableCell(\n            type: BTTableCellType.radio,\n            selected: true,\n            disabled: cell.disabled,\n          ),\n        ),\n      );\n\n  // ── field ─────────────────────────────────────────────────────────────────────\n\n  /// Full-width text input using [BTInput] (default variant).\n  Widget _fieldCell(BTDataTableCell cell) => BTInput(\n        controller: _fieldCtrl,\n        label: 'Title',\n        disabled: cell.disabled,\n        onChanged: (v) => _emit(\n          BTDataTableCell(\n            type: BTTableCellType.field,\n            value: v,\n            disabled: cell.disabled,\n          ),\n        ),\n      );\n\n  // ── dropdown ──────────────────────────────────────────────────────────────────\n\n  /// Inline [BTInputDropdown] for single-value selection.\n  Widget _dropdownCell(BTDataTableCell cell) {\n    final opts = cell.options.isEmpty ? _kDefaultDropdownOptions : cell.options;\n    return BTInputDropdown<String>(\n      label: cell.label ?? 'Title',\n      value: cell.value?.toString(),\n      disabled: cell.disabled,\n      items: opts\n          .map(\n            (o) => BTDropdownItem<String>(\n              value: o.value,\n              label: o.label,\n              disabled: cell.disabled,\n            ),\n          )\n          .toList(),\n      onChanged: (v) => _emit(\n        BTDataTableCell(\n          type: BTTableCellType.dropdown,\n          value: v,\n          options: cell.options,\n          disabled: cell.disabled,\n        ),\n      ),\n    );\n  }\n\n  static const _kDefaultDropdownOptions = [\n    BTDataTableOption(label: 'Title', value: 'title'),\n    BTDataTableOption(label: 'Label', value: 'label'),\n    BTDataTableOption(label: 'Draft', value: 'draft'),\n  ];\n\n  // ── multiple-selection ────────────────────────────────────────────────────────\n\n  /// Tag-based multi-value input using [BTInputMultipleField].\n  Widget _multipleSelectionCell(BTDataTableCell cell) =>\n      BTInputMultipleField<String>(\n        label: 'Title',\n        type: BTInputMultipleFieldType.scroll,\n        disabled: cell.disabled,\n        items: cell.options\n            .map((o) => BTDropdownItem<String>(value: o.value, label: o.label))\n            .toList(),\n        onChanged: (tags) => _emit(\n          BTDataTableCell(\n            type: BTTableCellType.multipleSelection,\n            options: tags\n                .map(\n                  (t) => BTDataTableOption(\n                    label: t.label,\n                    value: t.effectiveId,\n                  ),\n                )\n                .toList(),\n            disabled: cell.disabled,\n          ),\n        ),\n      );\n\n  // ── badge ─────────────────────────────────────────────────────────────────────\n\n  /// [BTBadge] — variant is driven by the badge label value.\n  Widget _badge(BTDataTableCell cell) {\n    final label = cell.badgeLabel ?? cell.label ?? 'Badge';\n    // Map common label values to badge variants (mirrors web showcase logic).\n    final variant = switch (label.toLowerCase()) {\n      'selected' || 'success' || 'approved' => BTBadgeVariant.success,\n      'waiting' || 'pending' || 'review' => BTBadgeVariant.waiting,\n      'reject' || 'rejected' || 'error' => BTBadgeVariant.reject,\n      _ => BTBadgeVariant.neutral,\n    };\n    return BTBadge(label: label, variant: variant);\n  }\n\n  // ── toggle ────────────────────────────────────────────────────────────────────\n\n  Widget _toggle(BTDataTableCell cell) => BTSwitchField(\n        value: cell.checked,\n        size: BTSwitchFieldSize.sm,\n        disabled: cell.disabled,\n        onChanged: cell.disabled\n            ? null\n            : (v) => _emit(\n                  BTDataTableCell(\n                    type: BTTableCellType.toggle,\n                    checked: v,\n                    disabled: cell.disabled,\n                  ),\n                ),\n      );\n}\n\n// ─── Internal: option cell ────────────────────────────────────────────────────\n\n/// Option cell — renders a row of [BTRadioButton] widgets, one per option.\n///\n/// Matches Figma node 2349-2726 (\"Type=Option\"): two radio buttons side by\n/// side with their labels, separated by a 16dp gap.\n///\n/// Used exclusively by [BTTableItem] for [BTTableCellType.option] cells.\nclass _BTTableOption extends StatelessWidget {\n  const _BTTableOption({\n    required this.cell,\n    required this.onChanged,\n  });\n\n  final BTDataTableCell cell;\n  final void Function(String value) onChanged;\n\n  static const _kDefaultOptions = [\n    BTDataTableOption(label: 'Label A', value: 'a'),\n    BTDataTableOption(label: 'Label B', value: 'b'),\n  ];\n\n  @override\n  Widget build(BuildContext context) {\n    final opts = cell.options.isEmpty ? _kDefaultOptions : cell.options;\n    final selected = cell.value?.toString() ?? '';\n\n    return Wrap(\n      spacing: 12,\n      runSpacing: 4,\n      children: [\n        for (final opt in opts)\n          BTRadioButton<String>(\n            groupValue: selected,\n            value: opt.value,\n            label: opt.label,\n            disabled: cell.disabled,\n            // onChanged is required non-nullable; disabled flag suppresses taps.\n            onChanged: onChanged,\n          ),\n      ],\n    );\n  }\n}\n"
    },
    {
      "path": "internal/bt_table_row.dart",
      "target": "@flutterBase/data-table/internal/bt_table_row.dart",
      "type": "registry:ui",
      "content": "// internal — data row widget for BTDataTable (not exported)\n// Supports a single visible tree row. The parent table flattens expanded rows.\n// ignore_for_file: prefer_int_literals\n\nimport 'package:btech_tokens/btech_tokens.dart';\nimport '../../checkbox/checkbox.widget.dart';\nimport 'package:btech_ui/src/components/organisms/data_table/bt_data_table.types.dart';\nimport 'package:btech_ui/src/components/organisms/data_table/internal/bt_synced_horizontal_viewport.dart';\nimport 'package:btech_ui/src/components/organisms/data_table/internal/bt_table_item.dart';\nimport 'package:flutter/foundation.dart';\nimport 'package:flutter/material.dart';\n\n/// Default mixed-content header row height.\nconst double kRowHeight = 52.0;\n\n/// Default mixed-content data row minimum height.\nconst double kDataRowControlHeight = 68.0;\n\n/// Checkbox column width.\nconst double kCheckboxWidth = 40.0;\n\n/// Renders a single data row.\n///\n/// Left (checkbox + fixedLeft cols) and right (fixedRight cols) sections are\n/// pinned. The middle section scrolls horizontally with a shared offset so all\n/// rows stay in sync.\nclass BTTableRow extends StatefulWidget {\n  const BTTableRow({\n    required this.row,\n    required this.columns,\n    required this.columnWidths,\n    required this.depth,\n    required this.variant,\n    required this.hasCheckbox,\n    required this.isSelected,\n    required this.expandedKeys,\n    required this.selectedRows,\n    required this.fixedLeft,\n    required this.fixedRight,\n    required this.hScrollOffset,\n    required this.onHorizontalOffsetChanged,\n    required this.middleW,\n    required this.visibleMiddleW,\n    required this.rowMinHeight,\n    required this.showBottomDivider,\n    this.onCheckRow,\n    this.onCellChange,\n    this.onExpandedKeysChanged,\n    super.key,\n  });\n\n  final BTDataTableRow row;\n  final List<BTDataTableColumn> columns;\n  final List<double> columnWidths;\n  final int depth;\n  final BTDataTableVariant variant;\n  final bool hasCheckbox;\n  final bool isSelected;\n  final Map<String, bool> expandedKeys;\n  final List<String> selectedRows;\n\n  /// Number of data columns pinned from the left (does not count checkbox).\n  final int fixedLeft;\n\n  /// Number of data columns pinned from the right.\n  final int fixedRight;\n\n  /// Shared horizontal scroll controller — offset drives middle translation.\n  final ValueListenable<double> hScrollOffset;\n  final ValueChanged<double> onHorizontalOffsetChanged;\n\n  /// Total pixel width of all middle (scrollable) columns combined.\n  final double middleW;\n\n  /// Visible (viewport) width of the middle section — used as SizedBox width\n  /// so the ClipRect clips correctly without needing Expanded.\n  final double visibleMiddleW;\n\n  final double rowMinHeight;\n\n  final bool showBottomDivider;\n\n  final void Function(String rowId)? onCheckRow;\n  final void Function(BTDataTableCellChangePayload)? onCellChange;\n  final void Function(Map<String, bool>)? onExpandedKeysChanged;\n\n  @override\n  State<BTTableRow> createState() => _BTTableRowState();\n}\n\nclass _BTTableRowState extends State<BTTableRow> {\n  bool _isHovered = false;\n\n  bool get _enableHover => switch (defaultTargetPlatform) {\n        TargetPlatform.macOS ||\n        TargetPlatform.windows ||\n        TargetPlatform.linux =>\n          true,\n        _ => false,\n      };\n\n  bool get _hasChildren =>\n      widget.row.children != null && widget.row.children!.isNotEmpty;\n\n  bool get _isExpanded => widget.expandedKeys[widget.row.id] ?? false;\n\n  /// Tri-state checkbox for rows with children.\n  bool? get _checkState {\n    if (!widget.hasCheckbox) return false;\n    if (!_hasChildren) {\n      return widget.selectedRows.contains(widget.row.id);\n    }\n    return _computeParentCheckState(widget.row, widget.selectedRows);\n  }\n\n  static bool? _computeParentCheckState(\n    BTDataTableRow row,\n    List<String> selected,\n  ) {\n    if (row.children == null || row.children!.isEmpty) {\n      return selected.contains(row.id);\n    }\n    final childStates = row.children!\n        .map((c) => _computeParentCheckState(c, selected))\n        .toList();\n    if (childStates.every((s) => s == true)) return true;\n    if (childStates.every((s) => s == false)) return false;\n    return null; // indeterminate\n  }\n\n  void _toggleExpand() {\n    final next = Map<String, bool>.from(widget.expandedKeys);\n    next[widget.row.id] = !_isExpanded;\n    widget.onExpandedKeysChanged?.call(next);\n  }\n\n  // ── Row background ─────────────────────────────────────────────────────────\n\n  Color _rowBg(BTColorTheme c) {\n    // Parent rows: highlight when ALL children are selected (checkState == true).\n    // Leaf rows: highlight when row id is in selectedRows.\n    final isSelected = _hasChildren ? _checkState == true : widget.isSelected;\n    if (isSelected) return c.brand.primarySubtle;\n    if (_isHovered) return c.bg.subtle;\n    return switch (widget.variant) {\n      BTDataTableVariant.noFill => Colors.transparent,\n      _ => _depthColor(c, widget.depth),\n    };\n  }\n\n  static Color _depthColor(BTColorTheme c, int depth) {\n    return switch (depth) {\n      1 => c.bg.primary,\n      2 => const Color(0xFFF9F9FA), // lGrey 50\n      3 => const Color(0xFFF3F4F5), // lGrey 100\n      4 => const Color(0xFFECEEF0), // lGrey 150\n      5 => const Color(0xFFE6E8EB), // lGrey 200\n      _ => const Color(0xFFDADDE1), // lGrey 300\n    };\n  }\n\n  // ── Expander indent for tree ───────────────────────────────────────────────\n\n  /// Left indent in the expander column: 4 + (depth-1) * 24 dp, matching BTTree.\n  double get _expanderIndent => 4.0 + (widget.depth - 1) * 24.0;\n\n  Widget _wrapHover(Widget child) {\n    if (!_enableHover) return child;\n    return MouseRegion(\n      cursor: SystemMouseCursors.basic,\n      onEnter: (_) => setState(() => _isHovered = true),\n      onExit: (_) => setState(() => _isHovered = false),\n      child: child,\n    );\n  }\n\n  // ── Section builders ───────────────────────────────────────────────────────\n\n  Widget _buildDataCell(\n    BuildContext context,\n    BTColorTheme c,\n    int colIndex, {\n    required bool showLeftDivider,\n  }) {\n    final col = widget.columns[colIndex];\n    final width = widget.columnWidths[colIndex];\n\n    final rawCell = widget.row.cells[col.key];\n    final BTDataTableCell cell;\n    if (rawCell is BTDataTableCell) {\n      cell = rawCell;\n    } else if (rawCell != null) {\n      cell = BTDataTableCell(\n        type: BTTableCellType.text,\n        value: rawCell.toString(),\n      );\n    } else {\n      cell = const BTDataTableCell(type: BTTableCellType.text, value: '');\n    }\n\n    final align = switch (col.align) {\n      BTDataTableColumnAlign.center => MainAxisAlignment.center,\n      BTDataTableColumnAlign.end => MainAxisAlignment.end,\n      BTDataTableColumnAlign.start => MainAxisAlignment.start,\n    };\n\n    // Expander cells are tappable on the whole cell, not just the arrow.\n    final isExpanderCell = col.expander && _hasChildren;\n\n    return SizedBox(\n        width: width,\n        child: GestureDetector(\n          onTap: isExpanderCell ? _toggleExpand : null,\n          child: Container(\n            constraints: BoxConstraints(minHeight: widget.rowMinHeight),\n            decoration: BoxDecoration(\n              border: showLeftDivider\n                  ? BorderDirectional(\n                      start: BorderSide(color: c.border.primary))\n                  : null,\n            ),\n            child: Padding(\n              padding: const EdgeInsets.all(8),\n              child: Row(\n                mainAxisAlignment: align,\n                crossAxisAlignment: CrossAxisAlignment.center,\n                children: [\n                  // Expander arrow (only in expander column)\n                  if (col.expander && (_hasChildren || widget.depth > 1)) ...[\n                    SizedBox(width: _expanderIndent),\n                    if (_hasChildren)\n                      SizedBox(\n                        width: 16.0,\n                        height: 16.0,\n                        child: AnimatedRotation(\n                          turns: _isExpanded ? 0.0 : -0.25,\n                          duration: const Duration(milliseconds: 150),\n                          child: Icon(\n                            Icons.keyboard_arrow_down_rounded,\n                            size: 16,\n                            color: c.text.secondary,\n                          ),\n                        ),\n                      )\n                    else\n                      const SizedBox(width: 16.0),\n                    const SizedBox(width: 4.0),\n                  ],\n\n                  // Cell content — BTTableItem renders raw content, no extra padding.\n                  Flexible(\n                    child: BTTableItem(\n                      column: col,\n                      rowId: widget.row.id,\n                      cell: cell,\n                      onCellChange: widget.onCellChange,\n                    ),\n                  ),\n                ],\n              ),\n            ),\n          ),\n        ));\n  }\n\n  @override\n  Widget build(BuildContext context) {\n    final c = context.btColor;\n    final bg = _rowBg(c);\n\n    final leftCount = widget.fixedLeft.clamp(0, widget.columns.length);\n    final rightCount =\n        widget.fixedRight.clamp(0, widget.columns.length - leftCount);\n    final middleEnd = widget.columns.length - rightCount;\n\n    final hasLeftSection = widget.hasCheckbox || leftCount > 0;\n    final hasRightSection = rightCount > 0;\n\n    // Pre-compute widths\n    final checkboxW = widget.hasCheckbox ? kCheckboxWidth : 0.0;\n    final leftColsW =\n        widget.columnWidths.sublist(0, leftCount).fold(0.0, (a, b) => a + b);\n\n    Widget? leftSection;\n    if (hasLeftSection) {\n      leftSection = _wrapHover(\n        Container(\n          width: checkboxW + leftColsW,\n          color: bg,\n          constraints: BoxConstraints(minHeight: widget.rowMinHeight),\n          child: Row(\n            crossAxisAlignment: CrossAxisAlignment.center,\n            children: [\n              if (widget.hasCheckbox)\n                Container(\n                  width: kCheckboxWidth,\n                  constraints: BoxConstraints(minHeight: widget.rowMinHeight),\n                  decoration: BoxDecoration(\n                    border: BorderDirectional(\n                      end: BorderSide(color: c.border.primary),\n                    ),\n                  ),\n                  child: Center(\n                    child: GestureDetector(\n                      onTap: () => widget.onCheckRow?.call(widget.row.id),\n                      child: BTCheckbox(\n                        checked: _checkState == true,\n                        indeterminate: _checkState == null,\n                        onChanged: (_) =>\n                            widget.onCheckRow?.call(widget.row.id),\n                      ),\n                    ),\n                  ),\n                ),\n              for (var i = 0; i < leftCount; i++)\n                _buildDataCell(\n                  context,\n                  c,\n                  i,\n                  showLeftDivider: i > 0,\n                ),\n            ],\n          ),\n        ),\n      );\n    }\n\n    final middleScrollable = ColoredBox(\n      color: bg,\n      child: ConstrainedBox(\n        constraints: BoxConstraints(minHeight: widget.rowMinHeight),\n        child: BTSyncedHorizontalViewport(\n          offsetListenable: widget.hScrollOffset,\n          onOffsetChanged: widget.onHorizontalOffsetChanged,\n          viewportWidth: widget.visibleMiddleW,\n          contentWidth: widget.middleW,\n          interactive: false,\n          child: Row(\n            crossAxisAlignment: CrossAxisAlignment.center,\n            children: [\n              for (var i = leftCount; i < middleEnd; i++)\n                _buildDataCell(\n                  context,\n                  c,\n                  i,\n                  showLeftDivider: leftCount > 0 || i > leftCount,\n                ),\n            ],\n          ),\n        ),\n      ),\n    );\n\n    final middleSection = _wrapHover(middleScrollable);\n\n    Widget? rightSection;\n    if (hasRightSection) {\n      final rightColsW =\n          widget.columnWidths.sublist(middleEnd).fold(0.0, (a, b) => a + b);\n      rightSection = _wrapHover(\n        Container(\n          width: rightColsW,\n          color: bg,\n          constraints: BoxConstraints(minHeight: widget.rowMinHeight),\n          child: Row(\n            crossAxisAlignment: CrossAxisAlignment.center,\n            children: [\n              for (var i = middleEnd; i < widget.columns.length; i++)\n                _buildDataCell(\n                  context,\n                  c,\n                  i,\n                  showLeftDivider: true,\n                ),\n            ],\n          ),\n        ),\n      );\n    }\n\n    final rowContent = Row(\n      crossAxisAlignment: CrossAxisAlignment.center,\n      children: [\n        if (leftSection != null) leftSection,\n        middleSection,\n        if (rightSection != null) rightSection,\n      ],\n    );\n\n    final rowWidget = (hasLeftSection || hasRightSection)\n        ? rowContent\n        : _wrapHover(\n            ColoredBox(\n              color: bg,\n              child: ConstrainedBox(\n                constraints: BoxConstraints(minHeight: widget.rowMinHeight),\n                child: BTSyncedHorizontalViewport(\n                  offsetListenable: widget.hScrollOffset,\n                  onOffsetChanged: widget.onHorizontalOffsetChanged,\n                  viewportWidth: widget.visibleMiddleW,\n                  contentWidth: widget.middleW,\n                  interactive: false,\n                  child: Row(\n                    crossAxisAlignment: CrossAxisAlignment.center,\n                    children: [\n                      for (var i = leftCount; i < middleEnd; i++)\n                        _buildDataCell(\n                          context,\n                          c,\n                          i,\n                          showLeftDivider: leftCount > 0 || i > leftCount,\n                        ),\n                    ],\n                  ),\n                ),\n              ),\n            ),\n          );\n\n    return Column(\n      mainAxisSize: MainAxisSize.min,\n      crossAxisAlignment: CrossAxisAlignment.stretch,\n      children: [\n        rowWidget,\n        if (widget.showBottomDivider)\n          Container(\n            height: 1.0,\n            color: c.border.primary,\n          ),\n      ],\n    );\n  }\n}\n"
    },
    {
      "path": "internal/bt_table_title.dart",
      "target": "@flutterBase/data-table/internal/bt_table_title.dart",
      "type": "registry:ui",
      "content": "// internal — header row for BTDataTable (not exported)\nimport 'package:btech_tokens/btech_tokens.dart';\nimport '../../checkbox/checkbox.widget.dart';\nimport 'package:btech_ui/src/components/organisms/data_table/bt_data_table.types.dart';\nimport 'package:btech_ui/src/components/organisms/data_table/internal/bt_synced_horizontal_viewport.dart';\nimport 'package:btech_ui/src/components/organisms/data_table/internal/bt_table_row.dart';\nimport 'package:flutter/foundation.dart';\nimport 'package:flutter/material.dart';\n\n/// Renders the sticky header row.\n///\n/// When [fixedLeft] > 0 or [hasCheckbox] is true, the left section is pinned.\n/// When [fixedRight] > 0 the right section is pinned.\n/// The middle section scrolls horizontally with the shared table offset.\nclass BTTableTitle extends StatelessWidget {\n  const BTTableTitle({\n    required this.columns,\n    required this.variant,\n    required this.hasCheckbox,\n    required this.checkAllState,\n    required this.columnWidths,\n    required this.fixedLeft,\n    required this.fixedRight,\n    required this.hScrollOffset,\n    required this.onHorizontalOffsetChanged,\n    required this.middleW,\n    required this.visibleMiddleW,\n    required this.headerMinHeight,\n    this.onCheckAll,\n    this.onSort,\n    super.key,\n  });\n\n  final List<BTDataTableColumn> columns;\n  final BTDataTableVariant variant;\n  final bool hasCheckbox;\n\n  /// Tri-state for the header checkbox (all / none / some rows selected).\n  final bool? checkAllState; // null = indeterminate, true = all, false = none\n\n  final List<double> columnWidths;\n\n  /// Number of data columns pinned from the left (does not count checkbox).\n  final int fixedLeft;\n\n  /// Number of data columns pinned from the right.\n  final int fixedRight;\n\n  final ValueListenable<double> hScrollOffset;\n  final ValueChanged<double> onHorizontalOffsetChanged;\n\n  /// Total pixel width of all middle (scrollable) columns combined.\n  final double middleW;\n\n  /// Visible (viewport) width of the middle section — used as SizedBox width.\n  final double visibleMiddleW;\n\n  final double headerMinHeight;\n\n  final VoidCallback? onCheckAll;\n  final void Function(String columnKey, BTDataTableSortDirection current)?\n      onSort;\n\n  @override\n  Widget build(BuildContext context) {\n    final c = context.btColor;\n    final headerBg = switch (variant) {\n      BTDataTableVariant.secondary => c.brand.primarySubtle,\n      BTDataTableVariant.noFill => Colors.transparent,\n      BTDataTableVariant.defaultVariant => c.bg.secondary,\n    };\n\n    final leftCount = fixedLeft.clamp(0, columns.length);\n    final rightCount = fixedRight.clamp(0, columns.length - leftCount);\n    final middleStart = leftCount;\n    final middleEnd = columns.length - rightCount;\n\n    final leftCols = columns.sublist(0, leftCount);\n    final middleCols = columns.sublist(middleStart, middleEnd);\n    final rightCols = rightCount > 0\n        ? columns.sublist(middleEnd)\n        : const <BTDataTableColumn>[];\n\n    final leftWidths = columnWidths.sublist(0, leftCount);\n    final middleWidths = columnWidths.sublist(middleStart, middleEnd);\n    final rightWidths =\n        rightCount > 0 ? columnWidths.sublist(middleEnd) : const <double>[];\n\n    final checkboxW = hasCheckbox ? kCheckboxWidth : 0.0;\n\n    final hasLeftSection = hasCheckbox || leftCount > 0;\n    final hasRightSection = rightCount > 0;\n    final maxHorizontalOffset =\n        middleW > visibleMiddleW ? middleW - visibleMiddleW : 0.0;\n\n    // ── Left cells ─────────────────────────────────────────────────────────────\n    // Header height is content-driven (Padding all:8 per cell + IntrinsicHeight on outer Row).\n    // headerMinHeight only acts as a floor for short labels.\n    Widget? leftWidget;\n    if (hasLeftSection) {\n      final leftColsW = leftWidths.fold(0.0, (a, b) => a + b);\n      leftWidget = Container(\n        width: checkboxW + leftColsW,\n        color: headerBg,\n        child: Row(\n          crossAxisAlignment: CrossAxisAlignment.stretch,\n          children: [\n            if (hasCheckbox)\n              Container(\n                width: kCheckboxWidth,\n                decoration: BoxDecoration(\n                  border: BorderDirectional(\n                    end: BorderSide(color: c.border.primary),\n                  ),\n                ),\n                child: Padding(\n                  padding: const EdgeInsets.all(8),\n                  child: Center(\n                    child: IgnorePointer(\n                      ignoring: onCheckAll == null,\n                      child: GestureDetector(\n                        onTap: onCheckAll,\n                        child: BTCheckbox(\n                          checked: checkAllState == true,\n                          indeterminate: checkAllState == null,\n                          onChanged: (_) => onCheckAll?.call(),\n                        ),\n                      ),\n                    ),\n                  ),\n                ),\n              ),\n            for (var i = 0; i < leftCols.length; i++)\n              _BTHeaderCell(\n                column: leftCols[i],\n                width: leftWidths[i],\n                bg: headerBg,\n                minHeight: headerMinHeight,\n                showLeftDivider: i > 0,\n                onSort: onSort,\n              ),\n          ],\n        ),\n      );\n    }\n\n    final middleScrollable = ColoredBox(\n      color: headerBg,\n      child: BTSyncedHorizontalViewport(\n        offsetListenable: hScrollOffset,\n        onOffsetChanged: onHorizontalOffsetChanged,\n        viewportWidth: visibleMiddleW,\n        contentWidth: middleW,\n        child: Row(\n          crossAxisAlignment: CrossAxisAlignment.stretch,\n          children: [\n            for (var i = 0; i < middleCols.length; i++)\n              _BTHeaderCell(\n                column: middleCols[i],\n                width: middleWidths[i],\n                bg: headerBg,\n                minHeight: headerMinHeight,\n                showLeftDivider: leftCount > 0 || i > 0,\n                onSort: onSort,\n              ),\n          ],\n        ),\n      ),\n    );\n\n    // Shadow indicators for horizontal scroll are rendered at the table-frame\n    // level (BTDataTable._buildTableFrame). The header itself doesn't wrap\n    // a per-row shadow — that would only show on the header row and skip\n    // the data rows below (the bug this fix is patching).\n    final middleWidget = middleScrollable;\n\n    Widget? rightWidget;\n    if (hasRightSection) {\n      final rightColsW = rightWidths.fold(0.0, (a, b) => a + b);\n      rightWidget = Container(\n        width: rightColsW,\n        color: headerBg,\n        child: Row(\n          crossAxisAlignment: CrossAxisAlignment.stretch,\n          children: [\n            for (var i = 0; i < rightCols.length; i++)\n              _BTHeaderCell(\n                column: rightCols[i],\n                width: rightWidths[i],\n                bg: headerBg,\n                minHeight: headerMinHeight,\n                showLeftDivider: true,\n                onSort: onSort,\n              ),\n          ],\n        ),\n      );\n    }\n\n    // IntrinsicHeight + Row.stretch: header height = tallest cell (driven by\n    // header label + 8px padding). All sections share that height per row.\n    return IntrinsicHeight(\n      child: Row(\n        crossAxisAlignment: CrossAxisAlignment.stretch,\n        children: [\n          if (leftWidget != null) leftWidget,\n          middleWidget,\n          if (rightWidget != null) rightWidget,\n        ],\n      ),\n    );\n  }\n}\n\nclass _BTHeaderCell extends StatelessWidget {\n  const _BTHeaderCell({\n    required this.column,\n    required this.width,\n    required this.bg,\n    required this.minHeight,\n    required this.showLeftDivider,\n    this.onSort,\n  });\n\n  final BTDataTableColumn column;\n  final double width;\n  final Color bg;\n  final double minHeight;\n  final bool showLeftDivider;\n  final void Function(String key, BTDataTableSortDirection current)? onSort;\n\n  @override\n  Widget build(BuildContext context) {\n    final c = context.btColor;\n    // Sort icon ALWAYS visible (matches web Figma 2373-11580). Tap only fires\n    // the callback when the column opts in via `sortable: true`.\n    final isSortable = column.sortable && onSort != null;\n    final dir = column.sortDirection;\n\n    final labelText = Text(\n      column.label.toUpperCase(),\n      style: TextStyle(\n        fontFamily: BTTypography.fontFamily,\n        fontSize: 11.0,\n        fontWeight: FontWeight.w600,\n        height: 16 / 11,\n        color: c.text.secondary,\n        letterSpacing: 0.3,\n      ),\n      overflow: TextOverflow.ellipsis,\n    );\n\n    // Header layout: label left, sort icon right — space-between always\n    // (matches Figma 2373-11580). `column.align` only affects data cells.\n    Widget headerContent = Row(\n      mainAxisAlignment: MainAxisAlignment.spaceBetween,\n      crossAxisAlignment: CrossAxisAlignment.center,\n      children: [\n        Expanded(child: labelText),\n        const SizedBox(width: 4),\n        _SortIcon(direction: dir, color: c.text.secondary),\n      ],\n    );\n\n    // Wrap in GestureDetector only when sortable — non-sortable still shows\n    // the icon but doesn't react to taps.\n    if (isSortable) {\n      headerContent = MouseRegion(\n        cursor: SystemMouseCursors.click,\n        child: GestureDetector(\n          onTap: () => onSort!(column.key, dir),\n          behavior: HitTestBehavior.opaque,\n          child: headerContent,\n        ),\n      );\n    }\n\n    return Container(\n      width: width,\n      constraints: BoxConstraints(minHeight: minHeight),\n      decoration: BoxDecoration(\n        color: bg,\n        border: showLeftDivider\n            ? BorderDirectional(start: BorderSide(color: c.border.primary))\n            : null,\n      ),\n      child: Padding(\n        padding: const EdgeInsets.all(8),\n        child: headerContent,\n      ),\n    );\n  }\n}\n\nclass _SortIcon extends StatelessWidget {\n  const _SortIcon({required this.direction, required this.color});\n\n  final BTDataTableSortDirection direction;\n  final Color color;\n\n  @override\n  Widget build(BuildContext context) {\n    switch (direction) {\n      case BTDataTableSortDirection.asc:\n        return Icon(Icons.arrow_upward_rounded, size: 12, color: color);\n      case BTDataTableSortDirection.desc:\n        return Icon(Icons.arrow_downward_rounded, size: 12, color: color);\n      case BTDataTableSortDirection.none:\n        return Icon(Icons.unfold_more_rounded,\n            size: 12, color: color.withOpacity(0.5));\n    }\n  }\n}\n"
    }
  ]
}